rootoidb/__init__.py
rootoidb/create/__init__.py
rootoidb/encrypter/__init__.py
rootoidb/flask/__init__.py
rootoidb-0.5.0.dist-info/License.txt
rootoidb-0.5.0.dist-info/METADATA
rootoidb-0.5.0.dist-info/WHEEL
rootoidb-0.5.0.dist-info/top_level.txt
rootoidb-0.5.0.dist-info/RECORD
