Metadata-Version: 2.1
Name: rootoidb
Version: 0.5.0
Summary: THIS IS NOSQL DATABASE
Home-page: https://github.com/akshaysethi2272005/rootoi
Author: Akshay Sethi
Author-email: akshaysethi0b10010@gmail.com
License: UNKNOWN
Keywords: rootoi,rootoidb,Rootoi,rootoi db,rootoidb,nosql,nosql db,rootoi nosql db
Platform: UNKNOWN
Classifier: Intended Audience :: Developers
Classifier: Programming Language :: Python :: 3
Classifier: Operating System :: Microsoft :: Windows
